invariant/__init__.py
invariant/__main__.py
invariant/analyzer/__init__.py
invariant/analyzer/base_policy.py
invariant/analyzer/extras.py
invariant/analyzer/monitor.py
invariant/analyzer/policy.py
invariant/analyzer/remote_policy.py
invariant/analyzer/result.py
invariant/analyzer/traces.py
invariant/analyzer/examples/openai_agent_example.py
invariant/analyzer/examples/traces_example.py
invariant/analyzer/examples/agent_bugs/traceset.py
invariant/analyzer/examples/agent_flan/run.py
invariant/analyzer/language/ast.py
invariant/analyzer/language/linking.py
invariant/analyzer/language/optimizer.py
invariant/analyzer/language/parser.py
invariant/analyzer/language/scope.py
invariant/analyzer/language/types.py
invariant/analyzer/language/typing.py
invariant/analyzer/runtime/__init__.py
invariant/analyzer/runtime/evaluation.py
invariant/analyzer/runtime/evaluation_context.py
invariant/analyzer/runtime/function_cache.py
invariant/analyzer/runtime/functions.py
invariant/analyzer/runtime/input.py
invariant/analyzer/runtime/nodes.py
invariant/analyzer/runtime/patterns.py
invariant/analyzer/runtime/quantifier.py
invariant/analyzer/runtime/range.py
invariant/analyzer/runtime/rule.py
invariant/analyzer/runtime/runtime_errors.py
invariant/analyzer/runtime/span.py
invariant/analyzer/runtime/symbol_table.py
invariant/analyzer/runtime/interface/primitives.py
invariant/analyzer/runtime/utils/base.py
invariant/analyzer/runtime/utils/batching.py
invariant/analyzer/runtime/utils/code.py
invariant/analyzer/runtime/utils/invariant_attributes.py
invariant/analyzer/runtime/utils/moderation.py
invariant/analyzer/runtime/utils/ocr.py
invariant/analyzer/runtime/utils/pii.py
invariant/analyzer/runtime/utils/prompt_injections.py
invariant/analyzer/runtime/utils/secrets.py
invariant/analyzer/runtime/utils/sentence_similarity.py
invariant/analyzer/runtime/utils/copyright/copyright.py
invariant/analyzer/runtime/utils/copyright/software_licenses.py
invariant/analyzer/stdlib/invariant/__init__.py
invariant_ai-0.3.5.dist-info/licenses/LICENSE
invariant_ai-0.3.5.dist-info/METADATA
invariant_ai-0.3.5.dist-info/WHEEL
invariant_ai-0.3.5.dist-info/entry_points.txt
invariant_ai-0.3.5.dist-info/top_level.txt
invariant_ai-0.3.5.dist-info/RECORD
