Metadata-Version: 2.4
Name: invariant-ai
Version: 0.3.5
Summary: Invariant Guardrails
Requires-Python: <4,>=3.10
License-File: LICENSE
Requires-Dist: pydantic<3.0.0,>=2.9.2
Requires-Dist: requests<3,>=2.32.3
Requires-Dist: nltk<4,>=3.9.1
Requires-Dist: openai<2,>=1.54.4
Requires-Dist: Pillow<11,>=10.1.0
Requires-Dist: beautifulsoup4<5,>=4.12.3
Requires-Dist: invariant-sdk<0.0.12,>=0.0.11
Requires-Dist: diskcache<6,>=5.6.3
Requires-Dist: pexpect<5,>=4.9.0
Requires-Dist: lark>=1.1.9
Requires-Dist: termcolor>=2.4.0
Requires-Dist: pip>=24.0
Requires-Dist: pytest>=8.2.1
Requires-Dist: pytesseract>=0.3.13
Requires-Dist: aiohttp>=3.11.11
Requires-Dist: rich>=13.5.3
Provides-Extra: extras
Requires-Dist: openai-swarm<0.2,>=0.1.1; extra == "extras"
Requires-Dist: langgraph<0.3,>=0.2.53; extra == "extras"
Requires-Dist: langchain-openai>=0.2.10; extra == "extras"
Requires-Dist: langchain-community<0.4,>=0.3.9; extra == "extras"
Requires-Dist: anthropic<0.41,>=0.40.0; extra == "extras"
Requires-Dist: presidio-analyzer>=2.2.354; extra == "extras"
Requires-Dist: spacy>=3.7.5; extra == "extras"
Requires-Dist: semgrep>=1.78.0; extra == "extras"
Requires-Dist: langchain>=0.2.1; extra == "extras"
Requires-Dist: langchainhub>=0.1.16; extra == "extras"
Requires-Dist: transformers>=4.41.1; extra == "extras"
Requires-Dist: torch>=2.3.0; extra == "extras"
Requires-Dist: python-dotenv>=1.0.1; extra == "extras"
Requires-Dist: numpy>=1.26.4; extra == "extras"
Dynamic: license-file
